[
  {
    "id": "1",
    "name": "Bachelor"
  },
  {
    "id": "2",
    "name": "Masters"
  },
  {
    "id": "3",
    "name": "Doctorate"
  },
  {
    "id": "4",
    "name": "Non Degree Program"
  },
  {
    "id": "5",
    "name": "Diploma/Certification"
  },
  {
    "id": "6",
    "name": "A Level"
  },
  {
    "id": "7",
    "name": "O Level"
  },
  {
    "id": "8",
    "name": "Intermediate"
  },
  {
    "id": "9",
    "name": "Associate Degree"
  },
  {
    "id": "10",
    "name": "Foundation Degree"
  },
  {
    "id": "11",
    "name": "Diploma or Higher Education"
  },
  {
    "id": "13",
    "name": "Higher National Diploma"
  },
  {
    "id": "13",
    "name": "PhD"
  }
]
